scrollphathd/__init__.py
scrollphathd/is31fl3731.py
scrollphathd/api/__init__.py
scrollphathd/api/action.py
scrollphathd/api/http.py
scrollphathd/api/stoppablethread.py
scrollphathd/fonts/__init__.py
scrollphathd/fonts/font3x5.py
scrollphathd/fonts/font5x5.py
scrollphathd/fonts/font5x7.py
scrollphathd/fonts/font5x7smoothed.py
scrollphathd/fonts/font5x7unicode.py
scrollphathd/fonts/fontd3.py
scrollphathd/fonts/fontgauntlet.py
scrollphathd/fonts/fonthachicro.py
scrollphathd/fonts/fontorgan.py
scrollphathd-1.3.0.dist-info/LICENSE.txt
scrollphathd-1.3.0.dist-info/METADATA
scrollphathd-1.3.0.dist-info/WHEEL
scrollphathd-1.3.0.dist-info/top_level.txt
scrollphathd-1.3.0.dist-info/RECORD
