Metadata-Version: 2.1
Name: scrollphathd
Version: 1.3.0
Summary: Scroll pHAT HD Driver
Home-page: http://www.pimoroni.com
Author: Philip Howard
Author-email: phil@pimoroni.com
License: MIT
Keywords: Raspberry Pi LED
Platform: UNKNOWN
Classifier: Development Status :: 5 - Production/Stable
Classifier: Operating System :: POSIX :: Linux
Classifier: License :: OSI Approved :: MIT License
Classifier: Intended Audience :: Developers
Classifier: Programming Language :: Python :: 2.6
Classifier: Programming Language :: Python :: 2.7
Classifier: Programming Language :: Python :: 3
Classifier: Topic :: Software Development
Classifier: Topic :: System :: Hardware
Requires-Dist: numpy
Requires-Dist: smbus2
